pywire/__init__.py
pywire/bridge.py
pywire/browser.py
pywire/security.py
pywire/server.py
pywire/utils.py
pywire/web/bridge.js
pywire_eel-0.1.1.dist-info/licenses/LICENSE
pywire_eel-0.1.1.dist-info/METADATA
pywire_eel-0.1.1.dist-info/WHEEL
pywire_eel-0.1.1.dist-info/top_level.txt
pywire_eel-0.1.1.dist-info/RECORD
