Metadata-Version: 2.4
Name: pywire-eel
Version: 0.1.1
Summary: PyWire is a lightweight Python library that allows you to create simple desktop GUI applications using HTML, CSS, and JavaScript, while giving full access to Python’s functionality and libraries.
Home-page: https://github.com/Fadi002/pywire-eel
Author: Fadi002
License: MIT License
Requires-Python: >=3.7
License-File: LICENSE
Dynamic: home-page
Dynamic: license-file
Dynamic: requires-python
